{"reddit": {"motor-ad-7615": ["misterno7 - redd.it/qt7eob"], "brettbretterson_44": ["sdlemonade - redd.it/zs7z8e", "knocksunderboost - redd.it/zssj3h"], "larryloominlarge": ["oculiaeternam - redd.it/y4ag5n", "oculiaeternam - redd.it/y4bund", "ttt2k - redd.it/yrtwm2"], "bodymassagewatch": ["yourpointis - redd.it/x18z44", "depart9 - redd.it/xuvvqe", "bradend_5 - redd.it/12izuhu"], "seabass233": ["a_h_r_m_s - redd.it/od6d0b", "maritime_watch_guy - redd.it/11ckels"], "microscopic_cog_": ["sir_tapsalot - redd.it/zujrxl", "chuffnessment - redd.it/zzurcy"], "sammmmwich": ["greygrenade - redd.it/v53jd6", "e67 - redd.it/10q5x8b"], "tootundraforyou": ["federal_telephone_57 - redd.it/11cw9ic"], "nixonkb": ["LEGACY TRADE", "slayersjoker - redd.it/106uglp"], "axion87": ["LEGACY TRADE", "LEGACY TRADE", "LEGACY TRADE", "LEGACY TRADE", "zl1297 - redd.it/vauetu", "e67 - redd.it/vdu5yw", "alternativetomitch - redd.it/vdu5yw"], "zippy129": ["techsqueeze - redd.it/x6m6zx"], "tugger_nutzz": ["mammothhighlight - redd.it/y84ov0"], "cndnfighter": ["al3x3y89 - redd.it/wetn56"], "raider4-": ["teddyoctober - redd.it/w85n1k", "antoniotx - redd.it/xo4sva", "fit_profession - redd.it/xpvimf"], "omnomnomster": ["raidpanda - redd.it/ule2g8"], "efficientescape": ["avhva - redd.it/x225q0"], "erak606": ["mimi7323 - https://www.reddit.com/r/watchexchangecanada/comments/12r58zx"], "cheerios961": ["oculiaeternam - redd.it/114tt55"], "djay10star": ["jetshabsjets - redd.it/10zrexp"], "vinny0029": ["craigerstar - redd.it/106628h"], "doumy": ["LEGACY TRADE"], "strengr": ["w00ki3_85 - redd.it/10ac7b2"], "oldmanlucas": ["LEGACY TRADE"], "bglover29": ["apprehensive_bad_812 - redd.it/xg2wcl", "capital_ferret_1842 - redd.it/xg2yhs"], "mammothhighlight": ["tugger_nutzz - redd.it/y84ov0"], "cheeseit123": ["crownandconvention - redd.it/usqvb1"], "brandon198318": ["rocker_01 - redd.it/vs9p1m"], "fencerepee": ["LEGACY TRADE", "LEGACY TRADE"], "brad7659": ["LEGACY TRADE"], "blakhra": ["avhva - redd.it/10xk348"], "collegecutter": ["al3x3y89 - redd.it/11tnymo"], "hungry_footballer": ["bird_problem - redd.it/10vfcsn", "quicksilver777 - redd.it/11vpge3"], "jebpt": ["jcu187 - redd.it/10isifj"], "rupert_bloch": ["kickzilla - redd.it/11twlx0", "knocksunderboost - redd.it/11vvevd", "w00ki3_85 - redd.it/12cz26q", "inside_variation1594 - redd.it/12iu60s"], "frosty-ad295": ["postypete - redd.it/uuej03", "kojiflak - redd.it/vql12u", "inspectormike22 - redd.it/xg9yz3", "djqwerty13 - redd.it/xkease", "taziott - redd.it/10g6k2g"], "tr1-force": ["goofball_ - redd.it/w4t9s9"], "existing-roll9031": ["coubyman23 - redd.it/vxma6p"], "teraflu": ["al3x3y89 - redd.it/wiq2sw"], "a_commisso77": ["wiliamwith1fuckingl - https://www.reddit.com/r/watchexchangecanada/comments/12pgu6j"], "aurorainthekitchen": ["kangdh57 - redd.it/11cs7cw"], "rob-yo": ["aggressivesession312 - redd.it/11ymklp"], "gildo80": ["LEGACY TRADE", "LEGACY TRADE"], "pei_slander1974": ["antonytootall - redd.it/uxna8t", "antonytootall - redd.it/uxn444"], "e67": ["axion87 - redd.it/vdu5yw", "sammmmwich - redd.it/10q5x8b"], "talonnw": ["saskwatchman - redd.it/1178d8h"], "djqwerty13": ["frosty-ad295 - redd.it/xkease"], "balli977": ["the_costello_show - redd.it/vt6uqs"], "jacobsteam": ["netman2004 - redd.it/wcpebe"], "sorry_comfortable_51": ["razzmatazzvast6249 - redd.it/wvqqk0", "techsqueeze - redd.it/wnmyof", "throwawaytrper - redd.it/yon43h", "techsqueeze - redd.it/106qalu", "antonytootall - redd.it/10b3esi", "federal_telephone_57 - redd.it/10swjql", "throwawaytrper - redd.it/112au0t", "techsqueeze - redd.it/1196ht0"], "wirelessheaphones": ["LEGACY TRADE"], "gabpercos": ["jdosman - redd.it/zfg6c2"], "forkx1": ["abbreviationssea341 - redd.it/yp97vh"], "georgeschronos": ["ryanfromottawa - redd.it/tqo3t9"], "admirableblueberry67": ["liquidbusiness - redd.it/10vafsp"], "rich-ad8853": ["debsfg - redd.it/ygxye1"], "tacomaster3211": ["fallingtitans - redd.it/vfww1n", "androidisawesome - redd.it/wpfiub", "greatscot4224 - redd.it/ybxqr2", "taziott - redd.it/zgdnlx", "boilons - redd.it/12isxz3"], "epalii": ["elbigfatred - redd.it/112wpcj", "cheesybendito - redd.it/10zwnz7"], "sagwa99": ["LEGACY TRADE"], "mimi7323": ["LEGACY TRADE", "knocksunderboost - redd.it/vpw1ps", "dogboots88 - redd.it/10huhlv", "antonytootall - redd.it/10huhlv", "hoteliercanada - redd.it/10zrveg", "tarunscool - redd.it/1130v3d", "thegoalieking - redd.it/119e7ds", "extension-pirate3712 - redd.it/11olwrx", "erak606 - https://www.reddit.com/r/watchexchangecanada/comments/12r58zx"], "raidpanda": ["omnomnomster - redd.it/ule2g8"], "unsubstantial_event": ["gunpla-in-the-arctic - redd.it/uoxcmm", "gunpla-in-the-arctic - redd.it/utekcv", "jmkgl - redd.it/v21efq"], "ethanm101": ["misterno7 - redd.it/yiqfpl"], "eddie2311": ["craigerstar - redd.it/1065sz5"], "oculiaeternam": ["techsqueeze - redd.it/xawk20", "techsqueeze - redd.it/x9l90z", "abbreviationssea341 - redd.it/ycg66c", "hanandchewiee - redd.it/yq07wq", "larryloominlarge - redd.it/y4ag5n", "larryloominlarge - redd.it/y4bund", "z957q - redd.it/z6isym", "knocksunderboost - redd.it/ynvfbt", "metta_thinker - redd.it/zs0c1c", "cheerios961 - redd.it/114tt55", "senor-keefe - redd.it/11j2pvb", "malabar101 - redd.it/12n818k"], "kombuchacalm": ["antoniotx - redd.it/yblbvk"], "razzmatazzvast6249": ["sorry_comfortable_51 - redd.it/wvqqk0", "knocksunderboost - redd.it/zogsam"], "jacob_steadman": ["willing_letter_2920 - redd.it/ve4zpi"], "craigerstar": ["LEGACY TRADE", "LEGACY TRADE", "LEGACY TRADE", "LEGACY TRADE", "sajjaja - redd.it/vde3qx", "eddie2311 - redd.it/1065sz5", "vinny0029 - redd.it/106628h", "alternativetomitch - redd.it/117mipm"], "petgri": ["LEGACY TRADE", "phannypackv2 - redd.it/yzrj1x"], "elbigfatred": ["epalii - redd.it/112wpcj"], "peter7474": ["LEGACY TRADE", "LEGACY TRADE", "LEGACY TRADE", "LEGACY TRADE", "new-tie-1485 - redd.it/vp6wcf", "techsqueeze - redd.it/w0kxvc", "techsqueeze - redd.it/w4u8w6", "matterlee - redd.it/w7b0f6", "lesclousmalloy - redd.it/wyclfv"], "tbg010": ["roozbeh_m - redd.it/10jltjl"], "zackattackzack": ["websturr - redd.it/ushje3", "websturr - redd.it/usi6p2"], "naydanno": ["techsqueeze - redd.it/yij01y", "you-plastic - redd.it/zzcywr"], "shazoocow": ["techsqueeze - redd.it/vgqigd"], "tisse74": ["prominenttime - redd.it/xitki9"], "barry_dangles": ["affectionate-hall320 - redd.it/zzcmfx"], "matterlee": ["peter7474 - redd.it/w7b0f6", "awakeonfriday - redd.it/zwsdiu"], "nshield3": ["jdosman - redd.it/y5ugez"], "marselluswallace95": ["black-menthol - redd.it/10a1slj"], "lumm0x26": ["LEGACY TRADE"], "angry_guppy": ["zl1297 - redd.it/yuck6r"], "you-plastic": ["naydanno - redd.it/zzcywr"], "casual_bowling": ["aoi91 - redd.it/11r84ir"], "lucienpower": ["watchwhore204 - redd.it/ytfext", "debsfg - redd.it/10tq2wv"], "rocker_01": ["brandon198318 - redd.it/vs9p1m", "dcd617 - redd.it/x0wlo2", "foggy_rundown - redd.it/10eupsy"], "therealrod_": ["kazakthehound - redd.it/x3kapq", "darkstriker - redd.it/xfghea"], "apprehensive_bad_812": ["LEGACY TRADE", "bglover29 - redd.it/xg2wcl"], "inspectormike22": ["operation_difficult - redd.it/xgaw7w", "frosty-ad295 - redd.it/xg9yz3", "pharoah_petroc - redd.it/z6jrg5", "knocksunderboost - https://www.reddit.com/r/watchexchangecanada/comments/12qv0h7", "knocksunderboost - https://www.reddit.com/r/watchexchangecanada/comments/12qutjo"], "sovshop": ["foggy_rundown - redd.it/10ug94d", "goodchives - redd.it/11puwrb", "zl1297 - redd.it/128urpp"], "zsous": ["kiddo57 - redd.it/10m84si"], "rqte": ["adelegant5073 - redd.it/z0dx2c"], "the_canadian_comrade": ["chuffnessment - redd.it/11znl1w"], "sirreveller": ["legtayor - redd.it/11dp5ec"], "yourpointis": ["kickzilla - redd.it/vv3fhl", "bodymassagewatch - redd.it/x18z44"], "bc723": ["xyphium - redd.it/114w4rz"], "bali_hai": ["LEGACY TRADE"], "avhva": ["knocksunderboost - redd.it/vlvpx2", "efficientescape - redd.it/x225q0", "fit_profession - redd.it/zlgahc", "ttsmartypants - redd.it/10xk0cd", "blakhra - redd.it/10xk348"], "falafelking77": ["al3x3y89 - redd.it/xye44j"], "canzilla23": ["LEGACY TRADE", "LEGACY TRADE"], "toddable72": ["rezawrex - redd.it/10u2iv9"], "justin_ph": ["LEGACY TRADE"], "bigcyandinosaur": ["LEGACY TRADE"], "layer11": ["knocksunderboost - redd.it/wmqmar"], "techsqueeze": ["LEGACY TRADE", "LEGACY TRADE", "LEGACY TRADE", "LEGACY TRADE", "LEGACY TRADE", "jdosman - redd.it/v235wf", "anongta - redd.it/uq6x57", "phileoh - redd.it/v64z95", "cool_as_a_fish - redd.it/vcbi25", "full_fold_8732 - redd.it/vep3wq", "aclassyidiot - redd.it/uozn1c", "shazoocow - redd.it/vgqigd", "kickzilla - redd.it/vyid1r", "peter7474 - redd.it/w0kxvc", "peter7474 - redd.it/w4u8w6", "teddyoctober - redd.it/l1fyyf", "phannypackv2 - redd.it/vd8ja0", "goodchives - redd.it/x7ov6x", "full_fold_8732 - redd.it/x770t7", "full_fold_8732 - redd.it/x6xikj", "full_fold_8732 - redd.it/x771wx", "full_fold_8732 - redd.it/x6ykmi", "sorry_comfortable_51 - redd.it/wnmyof", "animatedcookie - redd.it/x6z1q3", "oculiaeternam - redd.it/xawk20", "knightcaeli - redd.it/x60ggb", "oculiaeternam - redd.it/x9l90z", "terapr0 - redd.it/xdrkq5", "zippy129 - redd.it/x6m6zx", "fela_wansumbooty - redd.it/xgxy0f", "antonytootall - redd.it/xtb8n6", "antonytootall - redd.it/xn7x4z", "goofball_ - redd.it/y2c1wr", "naydanno - redd.it/yij01y", "direwolf456 - redd.it/ztsuxl", "sorry_comfortable_51 - redd.it/106qalu", "lipton_oyster - redd.it/105ehf8", "greygrenade - redd.it/117vabc", "sorry_comfortable_51 - redd.it/1196ht0", "little-cockroach-190 - redd.it/11v47ah", "kickzilla - redd.it/11t9npc", "misterno7 - redd.it/11prhw1", "malfaisance - redd.it/121wfd0", "dickopf - redd.it/12g2avz"], "euphoriccessna22": ["chuffnessment - redd.it/11lm5f9"], "j_j_maelikson": ["foggy_rundown - redd.it/w678x3"], "shellder123": ["LEGACY TRADE"], "roirolii": ["rezawrex - redd.it/11owabj", "guppyf1 - redd.it/1287eeu"], "3ees": ["francissexpooch - redd.it/yzjmqz"], "zuzxi": ["pannylee - redd.it/vaty7b", "timtambaba - redd.it/wc899d"], "d3vilzadvoca8": ["cheesybendito - redd.it/xt1fzg"], "philtrapp": ["al3x3y89 - redd.it/xcu1q0"], "shmilkin": ["francissexpooch - redd.it/10cqxel"], "paninotime": ["bigbalzac74 - redd.it/yqpfuw"], "canadian123987": ["foggy_rundown - redd.it/10vjesr"], "websturr": ["zackattackzack - redd.it/ushje3", "zackattackzack - redd.it/usi6p2"], "thecorporatewatch": ["coubyman23 - redd.it/v0pviy"], "monkehc": ["rizzyp - redd.it/wkmzty", "gnarlsb - redd.it/10mraix"], "sbarkz3": ["cpsiddall - redd.it/vo7u3m"], "qcwatchdude": ["fit_profession - redd.it/z66vwg", "china_white - redd.it/zs0dh4", "ochagreenteaa - redd.it/11jhs5g"], "netholan": ["kotes95 - redd.it/11skacn"], "datguynamedjoe": ["jay_zalez - redd.it/xm67fe", "jay_zalez - redd.it/xm66oj"], "hotstud69": ["foggy_rundown - redd.it/10vjesr"], "lesclousmalloy": ["peter7474 - redd.it/wyclfv"], "metta_thinker": ["fit_profession - redd.it/vklipq", "oculiaeternam - redd.it/zs0c1c", "chuffnessment - redd.it/12bi44e"], "thevicman49": ["dstrctdbatman - redd.it/yf3l8t"], "fela_wansumbooty": ["techsqueeze - redd.it/xgxy0f"], "teddyoctober": ["raider4- - redd.it/w85n1k", "techsqueeze - redd.it/l1fyyf"], "androidisawesome": ["tacomaster3211 - redd.it/wpfiub", "knocksunderboost - redd.it/wykdqa", "knocksunderboost - redd.it/wykeye", "knocksunderboost - redd.it/wykcgj"], "seanhaylow": ["beautiful-film3804 - redd.it/11llq1n"], "attackdolphins": ["maximumsmoochy - redd.it/11qk41h"], "jcu187": ["jebpt - redd.it/10isifj"], "many_distribution_21": ["coolhip - redd.it/10ywfof", "mutakingprime - redd.it/1195k2k"], "fallingtitans": ["LEGACY TRADE", "tacomaster3211 - redd.it/vfww1n"], "darkstriker": ["therealrod_ - redd.it/xfghea", "animatedcookie - redd.it/xs3mhy"], "greygrenade": ["sammmmwich - redd.it/v53jd6", "zl1297 - redd.it/vav4je", "techsqueeze - redd.it/117vabc"], "accomplished_word774": ["toon-day - redd.it/vq485n"], "ejkarau": ["LEGACY TRADE"], "xyphium": ["bc723 - redd.it/114w4rz"], "eqt": ["china_white - redd.it/yd6fc1"], "netman2004": ["taziott - redd.it/wcplbe", "knocksunderboost - redd.it/wcpgzr", "jacobsteam - redd.it/wcpebe"], "abbreviationssea341": ["klutzy_grocery6498 - redd.it/y918y3", "oculiaeternam - redd.it/ycg66c", "forkx1 - redd.it/yp97vh"], "unlimitednights": ["aggressivesession312 - redd.it/10sal1f"], "aoi91": ["casual_bowling - redd.it/11r84ir", "arshnal - redd.it/11k9f97"], "throwawaytrper": ["sorry_comfortable_51 - redd.it/yon43h", "sorry_comfortable_51 - redd.it/112au0t"], "therundown88": ["sexinacanoe - redd.it/11ditv2"], "k1986": ["a_h_r_m_s - redd.it/12f4vqr"], "foggy_rundown": ["LEGACY TRADE", "LEGACY TRADE", "LEGACY TRADE", "LEGACY TRADE", "j_j_maelikson - redd.it/w678x3", "rocker_01 - redd.it/10eupsy", "hotstud69 - redd.it/10vjesr", "canadian123987 - redd.it/10vjesr", "sovshop - redd.it/10ug94d"], "nismo231": ["coubyman23 - redd.it/v1rux1"], "funk9k": ["chuffnessment - redd.it/zbkvfp", "deathbyninjadust - redd.it/113gh3d"], "r4ve": ["pickledherring3 - redd.it/gqin9p"], "buttersgems": ["rossimac007 - redd.it/yk7n7v"], "jonc0416": ["zl1297 - redd.it/ya8ch6"], "cooliomcknight": ["LEGACY TRADE"], "liquidbusiness": ["admirableblueberry67 - redd.it/10vafsp"], "affectionate-hall320": ["barry_dangles - redd.it/zzcmfx"], "powerlinetyler": ["LEGACY TRADE"], "charlesedwurdcheese": ["knocksunderboost - redd.it/v9hnxg"], "oyster904l": ["LEGACY TRADE"], "kkman2424": ["LEGACY TRADE"], "le_dkim": ["fuckhufflepuff - redd.it/11vyk4u"], "wristrolls": ["dickopf - redd.it/y2hk5q"], "ckim52": ["LEGACY TRADE", "LEGACY TRADE", "LEGACY TRADE", "da_fuzz - redd.it/uyay2y"], "cubbstgbl": ["klein001 - redd.it/127zay0"], "mcoh101": ["dickopf - redd.it/x9c7mh"], "toon-day": ["accomplished_word774 - redd.it/vq485n"], "alternativetomitch": ["axion87 - redd.it/vdu5yw", "taziott - redd.it/y3ft8u", "craigerstar - redd.it/117mipm"], "rizzyp": ["monkehc - redd.it/wkmzty"], "visibleghost": ["taziott - redd.it/11s1r88"], "cheesybendito": ["d3vilzadvoca8 - redd.it/xt1fzg", "epalii - redd.it/10zwnz7"], "public_positive8415": ["asdfnonsense - redd.it/1110r4a"], "boilons": ["tacomaster3211 - redd.it/12isxz3"], "krym_": ["jetshabsjets - redd.it/12gqm6g"], "sexinacanoe": ["therundown88 - redd.it/11ditv2"], "carlosthesecond": ["LEGACY TRADE", "LEGACY TRADE"], "ottoman1986": ["jdosman - redd.it/v9na8z"], "stefans15": ["LEGACY TRADE"], "naived009": ["ttsmartypants - redd.it/wobtvz"], "capital_ferret_1842": ["bglover29 - redd.it/xg2yhs"], "vensersrevenge": ["bird_problem - redd.it/10vfcsn"], "francissexpooch": ["3ees - redd.it/yzjmqz", "shmilkin - redd.it/10cqxel"], "saskwatchman": ["talonnw - redd.it/1178d8h"], "goofball_": ["tr1-force - redd.it/w4t9s9", "techsqueeze - redd.it/y2c1wr"], "rezawrex": ["toddable72 - redd.it/10u2iv9", "recognitionrecent186 - redd.it/10ygcrj", "roirolii - redd.it/11owabj"], "operation_difficult": ["inspectormike22 - redd.it/xgaw7w", "jetshabsjets - redd.it/10i3eaq"], "gunpla-in-the-arctic": ["unsubstantial_event - redd.it/uoxcmm", "unsubstantial_event - redd.it/utekcv"], "hoteliercanada": ["tglo321 - redd.it/xk8wg9", "mimi7323 - redd.it/10zrveg"], "_kinel_": ["aclassyidiot - redd.it/uqy597"], "whamwhamwhozzle": ["antoniotx - redd.it/11vtwup"], "suspicious-gate-5619": ["brief-mirror-3851 - redd.it/z8de8p"], "misterno7": ["shkhw95 - redd.it/w1jnqy", "phannypackv2 - redd.it/xc1sgi", "ethanm101 - redd.it/yiqfpl", "straniya - redd.it/z90lha", "knocksunderboost - redd.it/zogsam", "asdfnonsense - redd.it/11pqxmj", "motor-ad-7615 - redd.it/qt7eob", "techsqueeze - redd.it/11prhw1", "gnus88 - https://www.reddit.com/r/watchexchangecanada/comments/11zuy2r"], "temporarilyalarming": ["max_siri - redd.it/w6em3j"], "ddr80": ["arshnal - redd.it/zvg1ba"], "klutzy_grocery6498": ["LEGACY TRADE", "abbreviationssea341 - redd.it/y918y3", "jdosman - redd.it/109aptu"], "knocksunderboost": ["charlesedwurdcheese - redd.it/v9hnxg", "avhva - redd.it/vlvpx2", "mimi7323 - redd.it/vpw1ps", "antoniotx - redd.it/vw9gjh", "straniya - redd.it/vvana2", "phannypackv2 - redd.it/w7akjf", "rgbpiano - redd.it/w7jr3w", "px-sodek - redd.it/wcufc3", "px-sodek - redd.it/wcu59d", "px-sodek - redd.it/wcu9qz", "layer11 - redd.it/wmqmar", "netman2004 - redd.it/wcpgzr", "simianone - redd.it/wm8rem", "androidisawesome - redd.it/wykdqa", "androidisawesome - redd.it/wykeye", "androidisawesome - redd.it/wykcgj", "oculiaeternam - redd.it/ynvfbt", "barelycontroversial - redd.it/zogsam", "knightcaeli - redd.it/zogsam", "misterno7 - redd.it/zogsam", "razzmatazzvast6249 - redd.it/zogsam", "noah1754 - redd.it/10ivbzr", "brettbretterson_44 - redd.it/zssj3h", "ak-now-ledge - redd.it/10iz33o", "jdosman - redd.it/10uqh6r", "federal_telephone_57 - redd.it/11envg6", "rupert_bloch - redd.it/11vvevd", "illairline7393 - redd.it/12970sc", "any-acanthocephala24 - redd.it/10iuiab", "stinkfist1234 - redd.it/12amvh8", "inspectormike22 - https://www.reddit.com/r/watchexchangecanada/comments/12qv0h7", "inspectormike22 - https://www.reddit.com/r/watchexchangecanada/comments/12qutjo"], "pickledherring3": ["r4ve - redd.it/gqin9p"], "pharoah_petroc": ["inspectormike22 - redd.it/z6jrg5"], "jmkgl": ["unsubstantial_event - redd.it/v21efq"], "aggressivesession312": ["unlimitednights - redd.it/10sal1f", "rob-yo - redd.it/11ymklp"], "dox_88": ["w00ki3_85 - redd.it/xm07bc"], "ttt2k": ["btov - redd.it/yci4cx", "slackmandu - redd.it/yvzzfr", "larryloominlarge - redd.it/yrtwm2"], "papaskittles": ["LEGACY TRADE"], "fit_profession": ["LEGACY TRADE", "LEGACY TRADE", "metta_thinker - redd.it/vklipq", "tglo321 - redd.it/vp56ex", "sdlemonade - redd.it/whvrid", "fuckhufflepuff - redd.it/wv1us6", "china_white - redd.it/xj7nw7", "raider4- - redd.it/xpvimf", "antoniotx - redd.it/xywjky", "qcwatchdude - redd.it/z66vwg", "5lant - redd.it/zixqcx", "avhva - redd.it/zlgahc", "a_h_r_m_s - redd.it/n7y1zk", "_disasterpony - redd.it/zrnnvv"], "twinsora": ["otpizzapeddler - redd.it/wb8ry4"], "thermulator": ["jdosman - redd.it/zr8bps"], "prominenttime": ["tisse74 - redd.it/xitki9", "notyourmothersdildo - redd.it/12q1hak"], "postypete": ["LEGACY TRADE", "frosty-ad295 - redd.it/uuej03"], "tglo321": ["LEGACY TRADE", "LEGACY TRADE", "LEGACY TRADE", "LEGACY TRADE", "LEGACY TRADE", "LEGACY TRADE", "straniya - redd.it/v6vb9r", "fit_profession - redd.it/vp56ex", "gnus88 - redd.it/w2cmv5", "strizzelean - redd.it/wkiqv4", "hoteliercanada - redd.it/xk8wg9", "kazakthehound - redd.it/10inggz", "warngs - redd.it/10wh0ih"], "knightcaeli": ["techsqueeze - redd.it/x60ggb", "knocksunderboost - redd.it/zogsam"], "gnus88": ["tglo321 - redd.it/w2cmv5", "jdosman - redd.it/wq7ct6", "canadiancruiser - redd.it/10occph", "misterno7 - https://www.reddit.com/r/watchexchangecanada/comments/11zuy2r"], "ttsmartypants": ["naived009 - redd.it/wobtvz", "avhva - redd.it/10xk0cd"], "vast_ad_5397": ["sdlemonade - redd.it/ukc3mc"], "new-tie-1485": ["peter7474 - redd.it/vp6wcf"], "fistbumpin": ["chuffnessment - redd.it/zzv8kq"], "antonytootall": ["pei_slander1974 - redd.it/uxna8t", "pei_slander1974 - redd.it/uxn444", "techsqueeze - redd.it/xtb8n6", "techsqueeze - redd.it/xn7x4z", "sorry_comfortable_51 - redd.it/10b3esi", "mimi7323 - redd.it/10huhlv"], "lipton_oyster": ["toomanyrobs - redd.it/100wfcj", "techsqueeze - redd.it/105ehf8"], "no-expectations24": ["chuffnessment - redd.it/z6xrdj"], "slackmandu": ["ttt2k - redd.it/yvzzfr"], "chuffnessment": ["loopsideratched - redd.it/yzejqn", "no-expectations24 - redd.it/z6xrdj", "funk9k - redd.it/zbkvfp", "wiliamwith1fuckingl - redd.it/zh07t0", "microscopic_cog_ - redd.it/zzurcy", "fistbumpin - redd.it/zzv8kq", "truthlesshunter - redd.it/11as02y", "euphoriccessna22 - redd.it/11lm5f9", "the_canadian_comrade - redd.it/11znl1w", "metta_thinker - redd.it/12bi44e"], "6_2_6_4": ["LEGACY TRADE"], "slayersjoker": ["nixonkb - redd.it/106uglp"], "s1l3ntst07m": ["jetshabsjets - redd.it/12gqhxe", "jetshabsjets - redd.it/12gqewd", "jetshabsjets - redd.it/12gqk9e"], "dickopf": ["mcoh101 - redd.it/x9c7mh", "wristrolls - redd.it/y2hk5q", "techsqueeze - redd.it/12g2avz"], "ochagreenteaa": ["ndlsmvmt - redd.it/11qw7zw", "qcwatchdude - redd.it/11jhs5g"], "deathbyninjadust": ["funk9k - redd.it/113gh3d"], "any-acanthocephala24": ["knocksunderboost - redd.it/10iuiab"], "willing_letter_2920": ["jacob_steadman - redd.it/ve4zpi"], "malabar101": ["oculiaeternam - redd.it/12n818k"], "illairline7393": ["knocksunderboost - redd.it/12970sc"], "fapoiefe": ["maritime_watch_guy - redd.it/113zmmy"], "bird_problem": ["LEGACY TRADE", "LEGACY TRADE", "zl1297 - redd.it/10kd7j7", "vensersrevenge - redd.it/10vfcsn", "hungry_footballer - redd.it/10vfcsn", "adelegant5073 - redd.it/110mmz6", "la_forme - redd.it/1186fhc", "chnaav - https://www.reddit.com/r/watchexchangecanada/comments/12pga2o"], "animatedcookie": ["techsqueeze - redd.it/x6z1q3", "darkstriker - redd.it/xs3mhy"], "black-menthol": ["LEGACY TRADE", "LEGACY TRADE", "jdosman - redd.it/vm5ilc", "taziott - redd.it/wczdli", "jdosman - redd.it/x6s6qf", "fuckhufflepuff - redd.it/104elfl", "fuckhufflepuff - redd.it/104egxf", "marselluswallace95 - redd.it/10a1slj"], "5lant": ["LEGACY TRADE", "LEGACY TRADE", "LEGACY TRADE", "fit_profession - redd.it/zixqcx"], "bboss-87": ["al3x3y89 - redd.it/x9cxkd"], "legtayor": ["LEGACY TRADE", "LEGACY TRADE", "sirreveller - redd.it/11dp5ec"], "goodchives": ["techsqueeze - redd.it/x7ov6x", "sovshop - redd.it/11puwrb"], "rossimac007": ["buttersgems - redd.it/yk7n7v"], "kangdh57": ["recognitionrecent186 - redd.it/w3f19h", "aurorainthekitchen - redd.it/11cs7cw"], "z957q": ["china_white - redd.it/yi1dsc", "oculiaeternam - redd.it/z6isym"], "kotes95": ["netholan - redd.it/11skacn"], "jb_1527": ["charliencn - redd.it/yrt3o5"], "charliencn": ["jb_1527 - redd.it/yrt3o5"], "dstrctdbatman": ["thevicman49 - redd.it/yf3l8t"], "nerdmachine": ["LEGACY TRADE"], "px-sodek": ["knocksunderboost - redd.it/wcufc3", "knocksunderboost - redd.it/wcu59d", "knocksunderboost - redd.it/wcu9qz"], "castleinthasky": ["fuckhufflepuff - redd.it/v8o2hz"], "recognitionrecent186": ["lebutdelavie - redd.it/upoe2t", "kangdh57 - redd.it/w3f19h", "sdlemonade - redd.it/xkhj7u", "rezawrex - redd.it/10ygcrj"], "full_fold_8732": ["LEGACY TRADE", "LEGACY TRADE", "techsqueeze - redd.it/vep3wq", "techsqueeze - redd.it/x770t7", "techsqueeze - redd.it/x6xikj", "techsqueeze - redd.it/x771wx", "techsqueeze - redd.it/x6ykmi"], "mbregg": ["LEGACY TRADE"], "wiliamwith1fuckingl": ["chuffnessment - redd.it/zh07t0", "a_commisso77 - https://www.reddit.com/r/watchexchangecanada/comments/12pgu6j"], "ryanfromottawa": ["georgeschronos - redd.it/tqo3t9"], "direwolf456": ["techsqueeze - redd.it/ztsuxl"], "maritime_watch_guy": ["fapoiefe - redd.it/113zmmy", "seabass233 - redd.it/11ckels", "antoniotx - https://www.reddit.com/r/watchexchangecanada/comments/12m6dvi"], "simianone": ["knocksunderboost - redd.it/wm8rem"], "aclassyidiot": ["techsqueeze - redd.it/uozn1c", "_kinel_ - redd.it/uqy597"], "china_white": ["fit_profession - redd.it/xj7nw7", "eqt - redd.it/yd6fc1", "z957q - redd.it/yi1dsc", "qcwatchdude - redd.it/zs0dh4"], "a_h_r_m_s": ["seabass233 - redd.it/od6d0b", "fit_profession - redd.it/n7y1zk", "k1986 - redd.it/12f4vqr"], "xxxbankai42xx": ["vaudeville12 - redd.it/11ae9fv"], "coubyman23": ["LEGACY TRADE", "LEGACY TRADE", "nismo231 - redd.it/v1rux1", "thecorporatewatch - redd.it/v0pviy", "existing-roll9031 - redd.it/vxma6p"], "canadiancruiser": ["gnus88 - redd.it/10occph"], "dogboots88": ["mimi7323 - redd.it/10huhlv"], "greatscot4224": ["tacomaster3211 - redd.it/ybxqr2"], "the_costello_show": ["balli977 - redd.it/vt6uqs"], "antoniotx": ["knocksunderboost - redd.it/vw9gjh", "zl1297 - redd.it/wz8kiq", "raider4- - redd.it/xo4sva", "fit_profession - redd.it/xywjky", "kombuchacalm - redd.it/yblbvk", "whamwhamwhozzle - redd.it/11vtwup", "maritime_watch_guy - https://www.reddit.com/r/watchexchangecanada/comments/12m6dvi"], "anongta": ["techsqueeze - redd.it/uq6x57"], "toomanyrobs": ["lipton_oyster - redd.it/100wfcj"], "bradend_5": ["bodymassagewatch - redd.it/12izuhu"], "tarunscool": ["mimi7323 - redd.it/1130v3d"], "-barry-lyndon-": ["LEGACY TRADE", "LEGACY TRADE"], "debsfg": ["doshibhai - redd.it/wb62c6", "rich-ad8853 - redd.it/ygxye1", "lucienpower - redd.it/10tq2wv"], "phannypackv2": ["LEGACY TRADE", "LEGACY TRADE", "jdosman - redd.it/vm9276", "knocksunderboost - redd.it/w7akjf", "techsqueeze - redd.it/vd8ja0", "timtambaba - redd.it/wwqljv", "misterno7 - redd.it/xc1sgi", "petgri - redd.it/yzrj1x"], "illustrious-screen37": ["LEGACY TRADE"], "awakeonfriday": ["matterlee - redd.it/zwsdiu"], "adelegant5073": ["rqte - redd.it/z0dx2c", "bird_problem - redd.it/110mmz6", "warngs - redd.it/11i6mcm"], "noah1754": ["knocksunderboost - redd.it/10ivbzr"], "straniya": ["tglo321 - redd.it/v6vb9r", "knocksunderboost - redd.it/vvana2", "misterno7 - redd.it/z90lha"], "taziott": ["LEGACY TRADE", "LEGACY TRADE", "netman2004 - redd.it/wcplbe", "black-menthol - redd.it/wczdli", "alternativetomitch - redd.it/y3ft8u", "zl1297 - redd.it/z3oaj7", "tacomaster3211 - redd.it/zgdnlx", "depart9 - redd.it/10dmg7v", "frosty-ad295 - redd.it/10g6k2g", "visibleghost - redd.it/11s1r88"], "da_fuzz": ["LEGACY TRADE", "ckim52 - redd.it/uyay2y"], "jetshabsjets": ["operation_difficult - redd.it/10i3eaq", "djay10star - redd.it/10zrexp", "s1l3ntst07m - redd.it/12gqhxe", "s1l3ntst07m - redd.it/12gqewd", "s1l3ntst07m - redd.it/12gqk9e", "krym_ - redd.it/12gqm6g"], "jdosman": ["LEGACY TRADE", "LEGACY TRADE", "techsqueeze - redd.it/v235wf", "ottoman1986 - redd.it/v9na8z", "black-menthol - redd.it/vm5ilc", "phannypackv2 - redd.it/vm9276", "gnus88 - redd.it/wq7ct6", "dcd617 - redd.it/x2f67r", "black-menthol - redd.it/x6s6qf", "ok_radish7390 - redd.it/xz8irq", "sdlemonade - redd.it/y5un7v", "nshield3 - redd.it/y5ugez", "gabpercos - redd.it/zfg6c2", "thermulator - redd.it/zr8bps", "klutzy_grocery6498 - redd.it/109aptu", "knocksunderboost - redd.it/10uqh6r"], "confident-car-8290": ["fuckhufflepuff - redd.it/10s6k0k"], "gab12309": ["LEGACY TRADE"], "extension-pirate3712": ["mimi7323 - redd.it/11olwrx"], "dry_personality3931": ["LEGACY TRADE"], "lebutdelavie": ["recognitionrecent186 - redd.it/upoe2t"], "fruitponchsamurai": ["LEGACY TRADE"], "asdfnonsense": ["public_positive8415 - redd.it/1110r4a", "misterno7 - redd.it/11pqxmj"], "senor-keefe": ["oculiaeternam - redd.it/11j2pvb"], "btov": ["ttt2k - redd.it/yci4cx"], "otpizzapeddler": ["twinsora - redd.it/wb8ry4"], "arshnal": ["ddr80 - redd.it/zvg1ba", "aoi91 - redd.it/11k9f97"], "strizzelean": ["tglo321 - redd.it/wkiqv4"], "bigbalzac74": ["paninotime - redd.it/yqpfuw"], "la_forme": ["bird_problem - redd.it/1186fhc", "oneninesixthree - redd.it/11w5vz3"], "zl1297": ["greygrenade - redd.it/vav4je", "axion87 - redd.it/vauetu", "antoniotx - redd.it/wz8kiq", "jonc0416 - redd.it/ya8ch6", "angry_guppy - redd.it/yuck6r", "taziott - redd.it/z3oaj7", "villiuski - redd.it/zzae2n", "bird_problem - redd.it/10kd7j7", "sovshop - redd.it/128urpp"], "crownandconvention": ["cheeseit123 - redd.it/usqvb1"], "kojiflak": ["frosty-ad295 - redd.it/vql12u"], "hanandchewiee": ["oculiaeternam - redd.it/yq07wq"], "vaudeville12": ["xxxbankai42xx - redd.it/11ae9fv"], "mutakingprime": ["many_distribution_21 - redd.it/1195k2k"], "truthlesshunter": ["chuffnessment - redd.it/11as02y"], "veloholic91": ["declan_h - redd.it/z85bcf"], "pete_86": ["LEGACY TRADE"], "barelycontroversial": ["knocksunderboost - redd.it/zogsam"], "pleasant-resort-2111": ["kazakthehound - redd.it/108l6py"], "gnarlsb": ["monkehc - redd.it/10mraix"], "warngs": ["tglo321 - redd.it/10wh0ih", "adelegant5073 - redd.it/11i6mcm"], "w00ki3_85": ["al3x3y89 - redd.it/x0t4hs", "strengr - redd.it/10ac7b2", "dox_88 - redd.it/xm07bc", "rupert_bloch - redd.it/12cz26q"], "brief-mirror-3851": ["suspicious-gate-5619 - redd.it/z8de8p"], "klein001": ["cubbstgbl - redd.it/127zay0"], "cool_as_a_fish": ["techsqueeze - redd.it/vcbi25"], "notyourmothersdildo": ["prominenttime - redd.it/12q1hak"], "roozbeh_m": ["tbg010 - redd.it/10jltjl"], "ak-now-ledge": ["knocksunderboost - redd.it/10iz33o"], "villiuski": ["zl1297 - redd.it/zzae2n"], "bezon67": ["timtambaba - redd.it/wwqtgb"], "eeksock": ["LEGACY TRADE"], "senor-fantastico": ["LEGACY TRADE"], "doshibhai": ["debsfg - redd.it/wb62c6"], "kickzilla": ["techsqueeze - redd.it/vyid1r", "yourpointis - redd.it/vv3fhl", "techsqueeze - redd.it/11t9npc", "rupert_bloch - redd.it/11twlx0"], "watchwhore204": ["lucienpower - redd.it/ytfext"], "thegoalieking": ["mimi7323 - redd.it/119e7ds"], "loopsideratched": ["chuffnessment - redd.it/yzejqn"], "phileoh": ["techsqueeze - redd.it/v64z95"], "cpsiddall": ["sbarkz3 - redd.it/vo7u3m"], "sir_tapsalot": ["microscopic_cog_ - redd.it/zujrxl"], "fuckhufflepuff": ["castleinthasky - redd.it/v8o2hz", "fit_profession - redd.it/wv1us6", "black-menthol - redd.it/104elfl", "black-menthol - redd.it/104egxf", "confident-car-8290 - redd.it/10s6k0k", "le_dkim - redd.it/11vyk4u"], "guppyf1": ["roirolii - redd.it/1287eeu"], "ndlsmvmt": ["ochagreenteaa - redd.it/11qw7zw"], "al3x3y89": ["pannylee - redd.it/up6y2s", "cndnfighter - redd.it/wetn56", "teraflu - redd.it/wiq2sw", "w00ki3_85 - redd.it/x0t4hs", "bboss-87 - redd.it/x9cxkd", "philtrapp - redd.it/xcu1q0", "falafelking77 - redd.it/xye44j", "tutorfree1906 - redd.it/xna9ax", "collegecutter - redd.it/11tnymo"], "shkhw95": ["misterno7 - redd.it/w1jnqy"], "kiddo57": ["zsous - redd.it/10m84si"], "chnaav": ["bird_problem - https://www.reddit.com/r/watchexchangecanada/comments/12pga2o"], "declan_h": ["veloholic91 - redd.it/z85bcf"], "malfaisance": ["LEGACY TRADE", "techsqueeze - redd.it/121wfd0"], "stinkfist1234": ["knocksunderboost - redd.it/12amvh8"], "kvn755": ["LEGACY TRADE", "LEGACY TRADE"], "federal_telephone_57": ["sorry_comfortable_51 - redd.it/10swjql", "knocksunderboost - redd.it/11envg6", "tootundraforyou - redd.it/11cw9ic"], "max_siri": ["temporarilyalarming - redd.it/w6em3j"], "maximumsmoochy": ["attackdolphins - redd.it/11qk41h"], "oneninesixthree": ["la_forme - redd.it/11w5vz3"], "timtambaba": ["zuzxi - redd.it/wc899d", "phannypackv2 - redd.it/wwqljv", "bezon67 - redd.it/wwqtgb"], "depart9": ["bodymassagewatch - redd.it/xuvvqe", "taziott - redd.it/10dmg7v"], "n0p3pp3r": ["LEGACY TRADE"], "rgbpiano": ["knocksunderboost - redd.it/w7jr3w"], "ok_radish7390": ["jdosman - redd.it/xz8irq"], "_disasterpony": ["fit_profession - redd.it/zrnnvv"], "pannylee": ["al3x3y89 - redd.it/up6y2s", "zuzxi - redd.it/vaty7b"], "quicksilver777": ["hungry_footballer - redd.it/11vpge3"], "dcd617": ["rocker_01 - redd.it/x0wlo2", "jdosman - redd.it/x2f67r"], "sdlemonade": ["LEGACY TRADE", "LEGACY TRADE", "vast_ad_5397 - redd.it/ukc3mc", "miginath - redd.it/vi8dag", "fit_profession - redd.it/whvrid", "recognitionrecent186 - redd.it/xkhj7u", "jdosman - redd.it/y5un7v", "brettbretterson_44 - redd.it/zs7z8e", "jayehuu - redd.it/zs81li"], "kazakthehound": ["therealrod_ - redd.it/x3kapq", "tglo321 - redd.it/10inggz", "pleasant-resort-2111 - redd.it/108l6py"], "jay_zalez": ["datguynamedjoe - redd.it/xm67fe", "datguynamedjoe - redd.it/xm66oj"], "miginath": ["sdlemonade - redd.it/vi8dag"], "little-cockroach-190": ["techsqueeze - redd.it/11v47ah"], "sajjaja": ["craigerstar - redd.it/vde3qx"], "tutorfree1906": ["al3x3y89 - redd.it/xna9ax"], "coolhip": ["many_distribution_21 - redd.it/10ywfof"], "jayehuu": ["sdlemonade - redd.it/zs81li"], "inside_variation1594": ["rupert_bloch - redd.it/12iu60s"], "beautiful-film3804": ["seanhaylow - redd.it/11llq1n"], "terapr0": ["techsqueeze - redd.it/xdrkq5"]}}